odoo/addons/server_action_sort/README.rst
odoo/addons/server_action_sort/__init__.py
odoo/addons/server_action_sort/__manifest__.py
odoo/addons/server_action_sort/demo/ir_actions_server.xml
odoo/addons/server_action_sort/i18n/fr.po
odoo/addons/server_action_sort/i18n/it.po
odoo/addons/server_action_sort/i18n/nl.po
odoo/addons/server_action_sort/i18n/nl_NL.po
odoo/addons/server_action_sort/i18n/server_action_sort.pot
odoo/addons/server_action_sort/models/__init__.py
odoo/addons/server_action_sort/models/ir_actions_server.py
odoo/addons/server_action_sort/models/ir_actions_server_sort_line.py
odoo/addons/server_action_sort/readme/CONFIGURE.md
odoo/addons/server_action_sort/readme/CONTRIBUTORS.md
odoo/addons/server_action_sort/readme/DESCRIPTION.md
odoo/addons/server_action_sort/readme/ROADMAP.md
odoo/addons/server_action_sort/readme/USAGE.md
odoo/addons/server_action_sort/security/ir.model.access.csv
odoo/addons/server_action_sort/static/description/icon.png
odoo/addons/server_action_sort/static/description/index.html
odoo/addons/server_action_sort/static/description/ir_actions_server_form.png
odoo/addons/server_action_sort/static/description/sale_order_form_after.png
odoo/addons/server_action_sort/static/description/sale_order_form_before.png
odoo/addons/server_action_sort/static/description/sale_order_tree.png
odoo/addons/server_action_sort/tests/__init__.py
odoo/addons/server_action_sort/tests/test_module.py
odoo/addons/server_action_sort/views/view_ir_actions_server.xml
odoo_addon_server_action_sort-18.0.1.0.0.5.dist-info/METADATA
odoo_addon_server_action_sort-18.0.1.0.0.5.dist-info/WHEEL
odoo_addon_server_action_sort-18.0.1.0.0.5.dist-info/top_level.txt
odoo_addon_server_action_sort-18.0.1.0.0.5.dist-info/RECORD
